iam_validator/__init__.py
iam_validator/__main__.py
iam_validator/__version__.py
iam_validator/checks/__init__.py
iam_validator/checks/action_condition_enforcement.py
iam_validator/checks/action_resource_matching.py
iam_validator/checks/action_validation.py
iam_validator/checks/condition_key_validation.py
iam_validator/checks/condition_type_mismatch.py
iam_validator/checks/full_wildcard.py
iam_validator/checks/mfa_condition_check.py
iam_validator/checks/not_action_not_resource.py
iam_validator/checks/policy_size.py
iam_validator/checks/policy_structure.py
iam_validator/checks/policy_type_validation.py
iam_validator/checks/principal_validation.py
iam_validator/checks/resource_validation.py
iam_validator/checks/sensitive_action.py
iam_validator/checks/service_wildcard.py
iam_validator/checks/set_operator_validation.py
iam_validator/checks/sid_uniqueness.py
iam_validator/checks/trust_policy_validation.py
iam_validator/checks/wildcard_action.py
iam_validator/checks/wildcard_resource.py
iam_validator/checks/utils/__init__.py
iam_validator/checks/utils/action_parser.py
iam_validator/checks/utils/policy_level_checks.py
iam_validator/checks/utils/sensitive_action_matcher.py
iam_validator/checks/utils/wildcard_expansion.py
iam_validator/commands/__init__.py
iam_validator/commands/analyze.py
iam_validator/commands/base.py
iam_validator/commands/cache.py
iam_validator/commands/completion.py
iam_validator/commands/download_services.py
iam_validator/commands/mcp.py
iam_validator/commands/post_to_pr.py
iam_validator/commands/query.py
iam_validator/commands/validate.py
iam_validator/core/__init__.py
iam_validator/core/access_analyzer.py
iam_validator/core/access_analyzer_report.py
iam_validator/core/aws_fetcher.py
iam_validator/core/check_registry.py
iam_validator/core/cli.py
iam_validator/core/codeowners.py
iam_validator/core/condition_validators.py
iam_validator/core/constants.py
iam_validator/core/diff_parser.py
iam_validator/core/finding_fingerprint.py
iam_policy_validator-1.15.6.dist-info/METADATA
iam_policy_validator-1.15.6.dist-info/WHEEL
iam_policy_validator-1.15.6.dist-info/entry_points.txt
iam_policy_validator-1.15.6.dist-info/licenses/LICENSE
iam_policy_validator-1.15.6.dist-info/RECORD
