Metadata-Version: 2.4
Name: iam-policy-validator
Version: 1.15.6
Summary: Validate AWS IAM policies for correctness and security using AWS Service Reference API
Project-URL: Homepage, https://github.com/boogy/iam-policy-validator
Project-URL: Documentation, https://boogy.github.io/iam-policy-validator
Project-URL: Repository, https://github.com/boogy/iam-policy-validator
Project-URL: Issues, https://github.com/boogy/iam-policy-validator/issues
Project-URL: Changelog, https://github.com/boogy/iam-policy-validator/blob/main/CHANGELOG.md
Author-email: boogy <0xboogy@gmail.com>
License: MIT
License-File: LICENSE
Keywords: aws,github-action,iam,policy,security,validation
Classifier: Development Status :: 5 - Production/Stable
Classifier: Intended Audience :: Developers
Classifier: Intended Audience :: System Administrators
Classifier: License :: OSI Approved :: MIT License
Classifier: Programming Language :: Python :: 3
Classifier: Programming Language :: Python :: 3.10
Classifier: Programming Language :: Python :: 3.11
Classifier: Programming Language :: Python :: 3.12
Classifier: Programming Language :: Python :: 3.13
Classifier: Programming Language :: Python :: 3.14
Classifier: Topic :: Security
Classifier: Topic :: Software Development :: Libraries :: Python Modules
Classifier: Topic :: System :: Systems Administration
Requires-Python: >=3.10
Requires-Dist: boto3>=1.28.0
Requires-Dist: botocore>=1.40.55
Requires-Dist: httpx[http2]>=0.27.0
Requires-Dist: pydantic>=2.0.0
Requires-Dist: pyyaml>=6.0
Requires-Dist: rich>=13.0.0
Provides-Extra: dev
Requires-Dist: mypy>=1.0.0; extra == 'dev'
Requires-Dist: pytest-asyncio>=0.21.0; extra == 'dev'
Requires-Dist: pytest-benchmark>=4.0.0; extra == 'dev'
Requires-Dist: pytest-cov>=7.0.0; extra == 'dev'
Requires-Dist: pytest>=7.0.0; extra == 'dev'
Requires-Dist: ruff>=0.1.0; extra == 'dev'
Requires-Dist: types-boto3; extra == 'dev'
Requires-Dist: types-pyyaml; extra == 'dev'
Provides-Extra: docs
Requires-Dist: mkdocs-gen-files>=0.5.0; extra == 'docs'
Requires-Dist: mkdocs-literate-nav>=0.6.0; extra == 'docs'
Requires-Dist: mkdocs-material>=9.5.0; extra == 'docs'
Requires-Dist: mkdocs>=1.6.0; extra == 'docs'
Requires-Dist: mkdocstrings[python]>=0.24.0; extra == 'docs'
Provides-Extra: mcp
Requires-Dist: fastmcp>=2.14.1; extra == 'mcp'
